LICENSE
README.md
setup.cfg
setup.py
xmelange/__init__.py
xmelange/conftest.py
xmelange.egg-info/PKG-INFO
xmelange.egg-info/SOURCES.txt
xmelange.egg-info/dependency_links.txt
xmelange.egg-info/top_level.txt
xmelange/examples/__init__.py
xmelange/examples/po.py
xmelange/xsd/__init__.py
xmelange/xsd/builtin_simple_types.py
xmelange/xsd/complex_types.py
xmelange/xsd/elements.py
xmelange/xsd/schema.py
xmelange/xsd/simple_types.py
xmelange/xsd_parser/__init__.py
xmelange/xsd_parser/xsd_parser.py